culib/__init__.py
culib/coils/__init__.py
culib/coils/basecoil.py
culib/coils/circularcoil.py
culib/coils/rectangularcoil.py
culib/field/__init__.py
culib/field/calc_func.py
culib/field/calc_func_3d.py
culib/field/df_field.py
culib/field/getters.py
culib/field/validate.py
culib/plot/__init__.py
culib/plot/charts.py
culib/plot/df_plot.py
culib/plot/plot_field.py
culib/plot/save.py
culib/plot/settings.py
culib/plot/titles.py
culib/utils/__init__.py
culib/utils/logs.py
culib/utils/types.py
culib/wires/__init__.py
culib/wires/basewire.py
culib/wires/data_wires.py
culib/wires/foilwire.py
culib/wires/roundwire.py
culib/wires/squarewire.py
culib-0.5.1.dist-info/METADATA
culib-0.5.1.dist-info/WHEEL
culib-0.5.1.dist-info/licenses/LICENSE
culib-0.5.1.dist-info/RECORD
