Metadata-Version: 2.4
Name: culib
Version: 0.5.1
Summary: Coils Utilities Library (CULib) is a Python package for modeling air-core electromagnet coils and calculating their physical characteristics based on their geometry and wire informations.
Author: Pierre Letousey
License:                     GNU GENERAL PUBLIC LICENSE
License-File: LICENSE
Keywords: bobbin,coil,electromagnet,field,magnetic,physics,simulation,wire
Classifier: Development Status :: 4 - Beta
Classifier: Intended Audience :: Science/Research
Classifier: Programming Language :: Python :: 3
Classifier: Topic :: Scientific/Engineering :: Physics
Requires-Python: >=3.11
Requires-Dist: altair>=5.1
Requires-Dist: numpy>=2
Requires-Dist: pandas>=2
Requires-Dist: scipy>=1.12
Requires-Dist: vl-convert-python>=1.7.0
Provides-Extra: dev
Requires-Dist: black>=22; extra == 'dev'
Requires-Dist: coverage>=7.10; extra == 'dev'
Requires-Dist: pytest>=8.4; extra == 'dev'
Requires-Dist: ruff>=0.12.0; extra == 'dev'
Provides-Extra: doc
Requires-Dist: mkdocs-bootswatch>=1.0; extra == 'doc'
Requires-Dist: mkdocs>=1.5; extra == 'doc'
Requires-Dist: mkdocstrings[python]<0.28,>=0.23; extra == 'doc'
